transformd/__init__.py
transformd/exceptions.py
transformd/transformer.py
transformd/utils.py
transformd/strategies/__init__.py
transformd/strategies/exclusion.py
transformd/strategies/inclusion.py
transformd-0.3.0.dist-info/METADATA
transformd-0.3.0.dist-info/WHEEL
transformd-0.3.0.dist-info/RECORD
