Metadata-Version: 2.1
Name: transformd
Version: 0.3.0
Summary: Transform dictionaries into whatever your heart desires (as long as it's another dictionary that kind of looks like the original dictionary)
Project-URL: Homepage, https://github.com/adamghill/transformd
Author: Adam Hill
Classifier: License :: OSI Approved :: MIT License
Classifier: Operating System :: OS Independent
Classifier: Programming Language :: Python :: 3
Requires-Python: >=3.8
Requires-Dist: mergedeep==1.3.4
Requires-Dist: typeguard==4.1.5
